[
    {
        "fovy": 60.0,
        "position": {
            "x": 13.905172348022461,
            "y": 1.9116922616958618,
            "z": 0.07811383903026581
        },
        "projection": 0,
        "target": {
            "x": 3.7117786407470703,
            "y": 2.142195463180542,
            "z": -0.12578125298023224
        },
        "type": "camera",
        "up": {
            "x": 0.0,
            "y": 1.0,
            "z": 0.0
        }
    },
    {
        "ambientColor": {
            "w": 1.0,
            "x": 1.0,
            "y": 1.0,
            "z": 1.0
        },
        "bloom": true,
        "bloomBrightness": 0.0,
        "bloomSamples": 3.0,
        "skyboxColor": {
            "w": 1.0,
            "x": 1.0,
            "y": 1.0,
            "z": 1.0
        },
        "skyboxPath": "assets/images/skybox/default skybox.hdr",
        "type": "world settings"
    },
    {
        "collider": true,
        "collider_type": 0,
        "damping": 0.0,
        "friction": 1.0,
        "id": 0,
        "is_dynamic": true,
        "lodEnabled": true,
        "mass": 1.0,
        "material_path": "",
        "mesh_type": 1,
        "model_path": "",
        "name": "Unnamed Entity",
        "normal_texture_path": "",
        "position": {
            "x": 0.0,
            "y": 3.000001907348633,
            "z": 0.0
        },
        "relative_position": {
            "x": 0.0,
            "y": 0.0,
            "z": 0.0
        },
        "rotation": {
            "x": 0.0,
            "y": 0.0,
            "z": 0.0
        },
        "roughness_texture_path": "",
        "scale": {
            "x": 1.0,
            "y": 1.0,
            "z": 1.0
        },
        "script_index": "",
        "script_path": "",
        "surface_material": {
            "DiffuseIntensity": 0.5,
            "Roughness": 0.5,
            "SpecularIntensity": 0.5,
            "SpecularTint": {
                "x": 1.0,
                "y": 1.0,
                "z": 1.0
            },
            "shininess": 0.5
        },
        "texture_path": "",
        "tiling": [
            1.0,
            1.0
        ],
        "type": "entity"
    },
    {
        "collider": true,
        "collider_type": 0,
        "damping": 0.0,
        "friction": 1.0,
        "id": 1,
        "is_dynamic": false,
        "lodEnabled": true,
        "mass": 1.0,
        "material_path": "project/game/file1.mat",
        "mesh_type": 1,
        "model_path": "",
        "name": "Unnamed Entity",
        "normal_texture_path": "",
        "position": {
            "x": 0.0,
            "y": 0.0,
            "z": 0.0
        },
        "relative_position": {
            "x": 0.0,
            "y": 0.0,
            "z": 0.0
        },
        "rotation": {
            "x": 0.0,
            "y": 0.0,
            "z": 0.0
        },
        "roughness_texture_path": "",
        "scale": {
            "x": 10.0,
            "y": 1.0,
            "z": 10.0
        },
        "script_index": "",
        "script_path": "",
        "surface_material": {
            "DiffuseIntensity": 1.0,
            "Roughness": 1.0,
            "SpecularIntensity": 1.0,
            "SpecularTint": {
                "x": 1.0,
                "y": 1.0,
                "z": 1.0
            },
            "shininess": 1.0
        },
        "texture_path": "",
        "tiling": [
            1.0,
            1.0
        ],
        "type": "entity"
    }
]